paynspray/__init__.py
paynspray/basex.py
paynspray/bin_manip.py
paynspray/codevert.py
paynspray/color.py
paynspray/compression.py
paynspray/encoding.py
paynspray/guid.py
paynspray/hash.py
paynspray/hex.py
paynspray/lmao.py
paynspray/octal.py
paynspray/rando.py
paynspray/table.py
paynspray/unicode.py
paynspray/win_color_console.py
paynspray/wordwrap.py
paynspray/xor.py
paynspray-0.2.10.dist-info/LICENSE
paynspray-0.2.10.dist-info/METADATA
paynspray-0.2.10.dist-info/WHEEL
paynspray-0.2.10.dist-info/top_level.txt
paynspray-0.2.10.dist-info/RECORD
