Metadata-Version: 2.1
Name: paynspray
Version: 0.2.10
Summary: Provides access to functions pertaining to text generation, manipulation, & presentation
Home-page: https://github.com/munshigroup/paynspray
Author: The Munshi Group
Author-email: support@munshigroup.com
License: UNKNOWN
Platform: UNKNOWN
Classifier: Programming Language :: Python :: 3
Classifier: Programming Language :: Python :: 2
Classifier: License :: OSI Approved :: MIT License
Classifier: Operating System :: OS Independent
Requires-Dist: amncore
